README
setup.py
tiddlywebplugins/__init__.py
tiddlywebplugins/spawner.py
tiddlywebplugins.spawner.egg-info/PKG-INFO
tiddlywebplugins.spawner.egg-info/SOURCES.txt
tiddlywebplugins.spawner.egg-info/dependency_links.txt
tiddlywebplugins.spawner.egg-info/namespace_packages.txt
tiddlywebplugins.spawner.egg-info/not-zip-safe
tiddlywebplugins.spawner.egg-info/requires.txt
tiddlywebplugins.spawner.egg-info/top_level.txt