Metadata-Version: 1.0
Name: tiddlywebplugins.spawner
Version: 0.6
Summary: A TiddlyWeb plugin that provides a factory for mounting tiddlyweb in Spawning.
Home-page: http://pypi.python.org/pypi/tiddlywebplugins.spawner
Author: Chris Dent
Author-email: cdent@peermore.com
License: UNKNOWN
Platform: Posix; MacOS X; Windows
